encdr/__init__.py
encdr/autoencoder.py
encdr/encdr.py
encdr-1.2.0.dist-info/METADATA
encdr-1.2.0.dist-info/WHEEL
encdr-1.2.0.dist-info/licenses/LICENSE
encdr-1.2.0.dist-info/RECORD
