Metadata-Version: 2.4
Name: encdr
Version: 1.2.0
Summary: A Python library for autoencoder-based dimensionality reduction with a scikit-learn compatible interface.
License-Expression: MIT
License-File: LICENSE
Requires-Python: >=3.12
Requires-Dist: lightning>=2.5.5
Requires-Dist: numpy>=1.21.0
Requires-Dist: scikit-learn>=1.7.2
Requires-Dist: torch>=2.0.0
